callistopy/__init__.py
callistopy/callistopy.py
callistopy-0.3.91.dist-info/licenses/LICENSE
callistopy-0.3.91.dist-info/METADATA
callistopy-0.3.91.dist-info/WHEEL
callistopy-0.3.91.dist-info/top_level.txt
callistopy-0.3.91.dist-info/RECORD
